aiovban_pyaudio/__init__.py
aiovban_pyaudio/enums.py
aiovban_pyaudio/player.py
aiovban_pyaudio/sender.py
aiovban_pyaudio/util.py
aiovban_pyaudio/scripts/__init__.py
aiovban_pyaudio/scripts/util.py
aiovban_pyaudio/scripts/audio_receiver/__init__.py
aiovban_pyaudio/scripts/audio_receiver/__main__.py
aiovban_pyaudio/scripts/audio_sender/__init__.py
aiovban_pyaudio/scripts/audio_sender/__main__.py
aiovban_pyaudio-0.1.0.dist-info/METADATA
aiovban_pyaudio-0.1.0.dist-info/WHEEL
aiovban_pyaudio-0.1.0.dist-info/entry_points.txt
aiovban_pyaudio-0.1.0.dist-info/top_level.txt
aiovban_pyaudio-0.1.0.dist-info/RECORD
