Metadata-Version: 2.1
Name: aiovban-pyaudio
Version: 0.1.0
Summary: A PyAudio wrapper for aiovban
Author-email: William Best <wmbest2@gmail.com>
Project-URL: Homepage, https://github.com/pypa/sampleproject
Project-URL: Issues, https://github.com/pypa/sampleproject/issues
Classifier: Programming Language :: Python :: 3
Classifier: License :: OSI Approved :: MIT License
Classifier: Operating System :: OS Independent
Requires-Python: >=3.10
Requires-Dist: aiovban
Requires-Dist: pyaudio
Provides-Extra: cli
Requires-Dist: setproctitle; extra == "cli"
